pomo/__init__.py
pomo/pomo.py
pomo_cli-1.0.0.dist-info/METADATA
pomo_cli-1.0.0.dist-info/WHEEL
pomo_cli-1.0.0.dist-info/entry_points.txt
pomo_cli-1.0.0.dist-info/top_level.txt
pomo_cli-1.0.0.dist-info/RECORD
